wsmx/__init_.py
wsmx/cli.py
wsmx/scaffold.json
wsmx/workspace_manager.py
wsmx-0.1.8.dist-info/entry_points.txt
wsmx-0.1.8.dist-info/LICENSE
wsmx-0.1.8.dist-info/METADATA
wsmx-0.1.8.dist-info/WHEEL
wsmx-0.1.8.dist-info/RECORD
