Metadata-Version: 2.3
Name: wsmx
Version: 0.1.8
Summary: Workspace Manager CLI for initializing standard workspace folders
Author: George Clayton Bennett
Author-email: george.bennett@memphistn.gov
Requires-Python: >=3.11
Classifier: Programming Language :: Python :: 3
Classifier: Programming Language :: Python :: 3.11
Classifier: Programming Language :: Python :: 3.12
Classifier: Programming Language :: Python :: 3.13
Requires-Dist: click (<8.1.7)
Requires-Dist: rich (<13.7.0)
Requires-Dist: toml (>=0.10.2,<0.11.0)
Requires-Dist: typer (>=0.12.3,<0.13.0)
